tcompress/__init__.py
tcompress/image.py
tcompress/main.py
tcompress/manage.py
tcompress/random.py
tcompress/time.py
tcompress-0.1.1.dist-info/LICENSE
tcompress-0.1.1.dist-info/METADATA
tcompress-0.1.1.dist-info/WHEEL
tcompress-0.1.1.dist-info/top_level.txt
tcompress-0.1.1.dist-info/RECORD
