Metadata-Version: 2.1
Name: tcompress
Version: 0.1.1
Summary: A small example package
Home-page: https://github.com/talalzeini/compress
Author: Talal El Zeini
Author-email: talalelzeini@gmail.com
Project-URL: Bug Tracker, https://github.com/talalzeini/compress/issues
Classifier: Programming Language :: Python :: 3
Classifier: License :: OSI Approved :: MIT License
Classifier: Operating System :: OS Independent
Requires-Python: >=3.6
License-File: LICENSE
